codeinterpreterapi/__init__.py
codeinterpreterapi/_patch_parser.py
codeinterpreterapi/chat_history.py
codeinterpreterapi/config.py
codeinterpreterapi/schema.py
codeinterpreterapi/session.py
codeinterpreterapi/chains/__init__.py
codeinterpreterapi/chains/extract_code.py
codeinterpreterapi/chains/modifications_check.py
codeinterpreterapi/chains/rm_dl_link.py
codeinterpreterapi/prompts/__init__.py
codeinterpreterapi/prompts/modifications_check.py
codeinterpreterapi/prompts/remove_dl_link.py
codeinterpreterapi/prompts/system_message.py
codeinterpreterapi-0.1.20.dist-info/METADATA
codeinterpreterapi-0.1.20.dist-info/WHEEL
codeinterpreterapi-0.1.20.dist-info/licenses/LICENSE
codeinterpreterapi-0.1.20.dist-info/RECORD
