Metadata-Version: 2.3
Name: codeinterpreterapi
Version: 0.1.20
Summary: CodeInterpreterAPI is an (unofficial) open source python interface for the ChatGPT CodeInterpreter.
Project-URL: Code, https://github.com/shroominic/codeinterpreter-api
Project-URL: Docs, https://shroominic.github.io/codeinterpreter-api
Author-email: Shroominic <contact@shroominic.com>
License: # MIT License
License-File: LICENSE
Keywords: api,chatgpt,codeboxapi,codeinterpreter,codeinterpreterapi,langchain
Classifier: License :: OSI Approved :: MIT License
Classifier: Programming Language :: Python :: 3.9
Classifier: Programming Language :: Python :: 3.10
Classifier: Programming Language :: Python :: 3.11
Classifier: Programming Language :: Python :: 3.12
Classifier: Topic :: Scientific/Engineering :: Artificial Intelligence
Requires-Python: <3.13,>=3.9.7
Requires-Dist: codeboxapi==0.1.19
Requires-Dist: langchain-openai
Requires-Dist: langchain<0.2,>=0.1
Requires-Dist: pyzmq==25.1.2
Provides-Extra: all
Requires-Dist: codeboxapi[all]; extra == 'all'
Requires-Dist: streamlit; extra == 'all'
Provides-Extra: frontend
Requires-Dist: streamlit; extra == 'frontend'
Provides-Extra: image-support
Requires-Dist: codeboxapi[image-support]; extra == 'image-support'
Provides-Extra: localbox
Requires-Dist: codeboxapi[local-support]; extra == 'localbox'
